CHANGES.txt
COPYRIGHT.txt
LICENSE.txt
README.txt
buildout.cfg
setup.py
bootstrap/bootstrap.py
src/megrok/__init__.py
src/megrok.chameleon.egg-info/PKG-INFO
src/megrok.chameleon.egg-info/SOURCES.txt
src/megrok.chameleon.egg-info/dependency_links.txt
src/megrok.chameleon.egg-info/namespace_packages.txt
src/megrok.chameleon.egg-info/not-zip-safe
src/megrok.chameleon.egg-info/requires.txt
src/megrok.chameleon.egg-info/top_level.txt
src/megrok/chameleon/README.txt
src/megrok/chameleon/__init__.py
src/megrok/chameleon/components.py
src/megrok/chameleon/configure.zcml
src/megrok/chameleon/expressions.py
src/megrok/chameleon/ftesting.zcml
src/megrok/chameleon/namespaces.py
src/megrok/chameleon/tests/__init__.py
src/megrok/chameleon/tests/test_megrok_chameleon.py
src/megrok/chameleon/tests/cpt_fixture/__init__.py
src/megrok/chameleon/tests/cpt_fixture/app.py
src/megrok/chameleon/tests/cpt_fixture/app_templates/cavepainting.cpt
src/megrok/chameleon/tests/cpt_fixture/app_templates/expressions.cpt
src/megrok/chameleon/tests/cpt_fixture/app_templates/food.cpt
src/megrok/chameleon/tests/cpt_fixture/app_templates/macromaster.cpt
src/megrok/chameleon/tests/cpt_fixture/app_templates/macrouser.cpt
src/megrok/chameleon/tests/cpt_fixture/app_templates/vars.cpt
src/megrok/chameleon/tests/cpt_fixture/static/test.css
src/megrok/chameleon/tests/genshi_fixture/__init__.py
src/megrok/chameleon/tests/genshi_fixture/app.py
src/megrok/chameleon/tests/genshi_fixture/app_templates/berries.cg
src/megrok/chameleon/tests/genshi_fixture/app_templates/cavepainting.cg
src/megrok/chameleon/tests/genshi_fixture/app_templates/food.cg
src/megrok/chameleon/tests/genshi_fixture/app_templates/gatherer.cg
src/megrok/chameleon/tests/genshi_fixture/app_templates/hunter.cgt
src/megrok/chameleon/tests/genshi_fixture/static/test.css