Metadata-Version: 1.0
Name: megrok.chameleon
Version: 0.5.1
Summary: Chameleon page template support for Grok
Home-page: http://pypi.python.org/pypi/megrok.chameleon
Author: Uli Fouquet
Author-email: grok-dev@zope.org
License: ZPL
Keywords: grok chameleon template
Platform: UNKNOWN
Classifier: Development Status :: 3 - Alpha
Classifier: Environment :: Web Environment
Classifier: Intended Audience :: Developers
Classifier: License :: OSI Approved :: Zope Public License
Classifier: Programming Language :: Python :: 2.5
Classifier: Operating System :: OS Independent
Classifier: Topic :: Internet :: WWW/HTTP
